{
"package_name" : "conduit",
"package_version" : "develop",
"package_source_dir" : "../../",
"spack_build_mode" : "uberenv-pkg",
"spack_configs_path": "scripts/uberenv_configs/spack_configs",
"spack_packages_path": "scripts/uberenv_configs/packages",
"spack_skip_externals": "true",
"spack_url": "https://github.com/spack/spack",
"spack_commit": "7c354095a94e524023119bd40726cd23c42e79d1",
"spack_host_config_patches":
 {
   "PYTHON_EXECUTABLE": "spack_view/bin/python3",
   "SPHINX_EXECUTABLE": "spack_view/bin/sphinx-build"
 }
}
